<?xml version="1.0" encoding="UTF-8"?>
<objects serializationModel="Studio.02.03.00">
	<object class="AudioFile" id="{068187a5-ff6b-4392-8d5d-621555012c82}">
		<property name="assetPath">
			<value>SR Music Nature characters Piano/14 synchron Steinway Salmon of knowledge_1.wav</value>
		</property>
		<property name="isStreaming">
			<value>true</value>
		</property>
		<property name="frequencyInKHz">
			<value>48</value>
		</property>
		<property name="channelCount">
			<value>2</value>
		</property>
		<property name="length">
			<value>81.935333333333332</value>
		</property>
		<relationship name="masterAssetFolder">
			<destination>{ebca4182-9fac-49cd-93d1-bfbca4c66617}</destination>
		</relationship>
	</object>
</objects>
